Workbook
Name \0: #REF!
Name \a: #REF!
Name \d: #REF!
Name \m: #REF!
Name \p: '[1]Bco. Internacional'!#REF!
Name __: #REF!
Name ___A320000: #REF!
Name ___A66000: #REF!
Name ___A69000: #REF!
Name ___A70000: #REF!
Name ___A99999: #REF!
Name ___M151060: #REF!
Name ___M152040: #REF!
Name ___M152050: '[2]Det. Rec. Prov. Locales {PPC}'!#REF!
Name ___MM11055: #REF!
Name ___MM23616: #REF!
Name ___RSE1: #REF!
Name ___RSE2: #REF!
Name __A320000: [3]CoberturaSeg!$A$32009
Name __A66000: [3]CoberturaSeg!$A$65009
Name __A69000: [3]CoberturaSeg!$A$65009
Name __A70000: [3]CoberturaSeg!$A$50009
Name __A99999: [3]CoberturaSeg!$A$32009
Name __DAT1: #REF!
Name __DAT10: #REF!
Name __DAT11: #REF!
Name __DAT12: #REF!
Name __DAT13: #REF!
Name __DAT14: #REF!
Name __DAT15: #REF!
Name __DAT16: #REF!
Name __DAT17: #REF!
Name __DAT18: #REF!
Name __DAT2: #REF!
Name __DAT3: #REF!
Name __DAT4: #REF!
Name __DAT5: #REF!
Name __DAT6: #REF!
Name __DAT7: #REF!
Name __DAT8: #REF!
Name __DAT9: #REF!
Name __M151060: #REF!
Name __M152040: #REF!
Name __M152050: '[2]Det. Rec. Prov. Locales {PPC}'!#REF!
Name __MM11055: #REF!
Name __MM23616: #REF!
Name __ND1: #REF!
Name __OB98008: '[4]OBB 31-dic-00'!#REF!
Name __OB98025: '[4]OBB 31-dic-00'!#REF!
Name __Pag1: #REF!
Name __pr1: #REF!
Name __RSE1: #REF!
Name __RSE2: #REF!
Name _02: #REF!
Name _10: #REF!
Name _1001: #REF!
Name _100101: #REF!
Name _10010101: #REF!
Name _1001010101: #REF!
Name _1001010102: #REF!

Sheet 136.07
N3: Preparado por: | O3: Revisado por: | P3: Ref.
N4: XX | O4: XX | P4: 136.07
B6: COMPAÑÍA MODELO S.A.
B7: VALIDACIÓN DE TRANSACCIONES CON COMPAÑÍAS FANTASMA
B8: AL 31 DE DICIEMBRE DE 20XX
B9: FECHA DE CORTE: _/_/20XX
B12: Objetivo:
B14: Determinar que la Compañía no registre operaciones con empresas fantasma.
B16: Base de decisión: Materialidad
C19: Preliminar | D19: Final
B20: General | C20: XXX.XXX | D20: XXX.XXX
B21: Desempeño | C21: XXX.XXX | D21: XXX.XXX
B22: Errores Triviales | C22: XXX.XXX | D22: XXX.XXX
B24: Procedimiento:
A26: 1.- | B26: Solicitar a la Compañía el detalle de compras al _/_/20XX.
A27: 2.- | B27: Descargar el listado de empresas fantasma a la fecha de nuestra revisión. ***(Incluir fecha de descarga)
A28: 3.- | B28: Verificar que la Compañía no se encuentre realizando transacciones con Compañías fantasma.
A29: 4.- | B29: Documentar el papel de trabajo y concluir en función al objetivo.
B32: Desarrollo:
G34: *** El número de filas, así como el formato depende del detalle de compras de la Compañía Modelo S.A.
B38: Base de compras | P38: Calculos según auditoría
B39: Nro. interno | C39: Tipo | D39: Fecha | E39: Secuencial | F39: RUC del proveedor | G39: Nombre proveedor | H39: TD | I39: TC | J39: Total del documento | K39: Subtotal | L39: Base 0% | M39: Base 12 % | N39: Total IVA | P39: RUC empresa fantasma | Q39: Empresa fantasma
P40: =+IFERROR(VLOOKUP(F40,'Listado empresas fantasmas SRI'!$B$2:$B$1057,1,0),0) -> 0 | Q40: =+IF(P40=0,"No","Si") -> No
P41: =+IFERROR(VLOOKUP(F41,'Listado empresas fantasmas SRI'!$B$2:$B$1057,1,0),0) -> 0 | Q41: =+IF(P41=0,"No","Si") -> No
P42: =+IFERROR(VLOOKUP(F42,'Listado empresas fantasmas SRI'!$B$2:$B$1057,1,0),0) -> 0 | Q42: =+IF(P42=0,"No","Si") -> No
P43: =+IFERROR(VLOOKUP(F43,'Listado empresas fantasmas SRI'!$B$2:$B$1057,1,0),0) -> 0 | Q43: =+IF(P43=0,"No","Si") -> No
P44: =+IFERROR(VLOOKUP(F44,'Listado empresas fantasmas SRI'!$B$2:$B$1057,1,0),0) -> 0 | Q44: =+IF(P44=0,"No","Si") -> No
P45: =+IFERROR(VLOOKUP(F45,'Listado empresas fantasmas SRI'!$B$2:$B$1057,1,0),0) -> 0 | Q45: =+IF(P45=0,"No","Si") -> No
P46: =+IFERROR(VLOOKUP(F46,'Listado empresas fantasmas SRI'!$B$2:$B$1057,1,0),0) -> 0 | Q46: =+IF(P46=0,"No","Si") -> No
P47: =+IFERROR(VLOOKUP(F47,'Listado empresas fantasmas SRI'!$B$2:$B$1057,1,0),0) -> 0 | Q47: =+IF(P47=0,"No","Si") -> No
P48: =+IFERROR(VLOOKUP(F48,'Listado empresas fantasmas SRI'!$B$2:$B$1057,1,0),0) -> 0 | Q48: =+IF(P48=0,"No","Si") -> No
P49: =+IFERROR(VLOOKUP(F49,'Listado empresas fantasmas SRI'!$B$2:$B$1057,1,0),0) -> 0 | Q49: =+IF(P49=0,"No","Si") -> No
B53: Resumen del análisis
B55: 1) ¿Proveedor es empresa fantasma?
B57: Si | D57: =+COUNTIF(Q40:Q49,B57) -> 0
B58: No | D58: =+COUNTIF(Q41:Q50,B58) -> 9
B62: Marcas de auditoría:
B64: Información proporcionada por el cliente
B65: Cálculos de Auditoría
B67: Verificaciones:
A69: A
A70: B
A71: C
B73: Notas aclaratorias:
A75: a)
A76: b)
A77: c)
B79: Observaciones:
A81: Obs. 1
A82: Obs. 2
A83: Obs. 3
B85: Conclusión:
B87: ***(Concluir en función al objetivo)

Sheet Listado empresas fantasmas SRI
A1: No. | B1: RUC | C1: RAZÓN SOCIAL | D1: TIPO DE CONTRIBUYENTE | E1: ZONA | F1: OFICIO 5 DÍAS NOTIFICADO | G1: FECHA DE NOTIFICACIÓN | H1: Nro. RESOLUCIÓN | I1: FECHA NOTIFICACIÓN | J1: CALIFICACIÓN | K1: ESTADO DEL RUC | L1: FECHA INICIO CALIFICACIÓN (**) | M1: FECHA FINALIZACIÓN CALIFICACIÓN (**) | N1: RESOLUCIÓN /SENTENCIA DE BAJA | O1: FECHA DE NOTIFICACIÓN RESOLUCIÓN /SENTENCIA | P1: N° DE OFICIO DE REACTIVACIÓN DE RUC | Q1: FECHA DE NOTIFICACIÓN | R1: ACEPTA / RECHAZA | S1: FECHA DE REACTIVACIÓN | T1: INSTANCIA DE IMPUGNACION | U1: ESTADO DE LA IMPUGNACIÓN
A2: 1 | B2: 1351650526001 | C2: BRAVO ACOSTA ANSELMO RAMON | D2: PERSONA NATURAL | E2: ZONA 1 | F2: PES-GTROGEI17-00000086-M | G2: 43003 | H2: DZ1-GPNRASN17-00000003-M | I2: 43047 | J2: Persona natural con actividades supuestas / transacciones inexistentes. | K2: SUSPENDIDO | T2: - | U2: -
A3: 2 | B3: 2191711079001 | C3: CONEFACONST CIA. LTDA. | D3: SOCIEDAD | E3: ZONA 1 | F3: NAC-DNCOPEC16-00161874-M | G3: 42601.339 | H3: DZ1-GSORIFV16-00000001 | I3: 42629 | J3: Sociedad con actividades supuestas o transacciones inexistentes | K3: SUSPENDIDO | L3: 40909 | M3: 42369 | T3: - | U3: -
A4: 3 | B4: 1727082578001 | C4: CONFORME MORALES LUIS FELIPE | D4: PERSONA NATURAL | E4: ZONA 1 | F4: PES-GTROGEC17-00000089-M | G4: 43007 | H4: DZ1-GPNRASN17-00000004-M | I4: 43052 | J4: Persona natural con actividades supuestas y transacciones inexistentes. | K4: SUSPENDIDO | T4: - | U4: -
A5: 4 | B5: 0802999060001 | C5: COROZO ESTUPIÑAN MAURICIO JOSE | D5: PERSONA NATURAL | E5: ZONA 1 | F5: PES-GTROGEC17-00000087-M | G5: 43005 | H5: DZ1-GPNRASN17-00000001-M | I5: 43052 | J5: Persona natural con actividades supuestas / transacciones inexistentes. | K5: SUSPENDIDO | T5: - | U5: -
A6: 5 | B6: 2100657770001 | C6: GAMEZ MENDEZ SILVIA CARMEN | D6: PERSONA NATURAL | E6: ZONA 1 | F6: PES-GTROGEC17-00000091-M | G6: 43007 | H6: DZ1-GPNRASN17-00000005-M | I6: 43052 | J6: Persona natural con actividades supuestas / transacciones inexistentes. | K6: SUSPENDIDO | T6: - | U6: -
A7: 6 | B7: 1792444713001 | C7: INCONCIV CONSTRUCCIONES CIA. LTDA. | D7: SOCIEDAD | E7: ZONA 1 | F7: DZ1-GSOOGEV17-00000002-M | G7: 43013 | H7: DZ1-GSORASV17-00000001-M | I7: 43021 | J7: Empresa inexistente / fantasma con actividades supuestas / transacciones inexistentes. | K7: PASIVO | T7: - | U7: -
A8: 7 | B8: 1723936066001 | C8: LOPEZ CORDERO DAVID ESTEBAN | D8: PERSONA NATURAL | E8: ZONA 1 | F8: PES-GTROGEC17-00000090-M | G8: 43003 | H8: DZ1-GPNRASO17-00000001-M | I8: 43047 | J8: Persona natural con actividades supuestas / transacciones inexistentes. | K8: SUSPENDIDO | M8: 42735 | N8: NAC-RRRRRVC22-00000172 | O8: 44677 | T8: RECURSOS DE REVISION | U8: FINALIZADO POR PERÍODOS
A9: 8 | B9: 1708816614001 | C9: VARGAS ALCIVAR FRANCISCO ISIDRO | D9: PERSONA NATURAL | E9: ZONA 1 | F9: PES-GTROGEN17-00000092-M | G9: 43003 | H9: DZ1-GPNRASN17-00000006-M | I9: 43068 | J9: Persona natural con actividades supuestas / transacciones inexistentes. | K9: SUSPENDIDO | M9: 43100 | N9: NAC-RRRRRVC20-00000295 | O9: 44218 | T9: RECURSOS DE REVISION | U9: FINALIZADO POR PERÍODOS
A10: 9 | B10: 0803139435001 | C10: ZAMBRANO MENDOZA KATIUSKA JACINTA | D10: PERSONA NATURAL | E10: ZONA 1 | F10: PES-GTROGEC17-00000088-M | G10: 43004 | H10: DZ1-GPNRASN17-00000002-M | I10: 43052 | J10: Persona natural con actividades supuestas / transacciones inexistentes. | K10: SUSPENDIDO | T10: - | U10: -
A11: 10 | B11: 1500198609001 | C11: ARELLANO MAFLA HEISTEIN MENTOR | D11: PERSONA NATURAL | E11: ZONA 2 | F11: NAC-DNCOIOG16-00005398 | G11: 42685 | H11: DZ2-GTRRSAC16-00000005-M | I11: 42705 | J11: Persona natural con actividades supuestas y/o transacciones inexistentes. | K11: SUSPENDIDO | T11: RECLAMOS | U11: FINALIZADO SE RATIFICA
A12: 11 | B12: 1704462280001 | C12: ARELLANO MAFLA JUAN MILTON | D12: PERSONA NATURAL | E12: ZONA 2 | F12: NAC-DNCOIOG16-00005422 | G12: 42685 | H12: DZ2-GTRRSAC16-00000001-M | I12: 42705 | J12: Persona natural con actividades supuestas y/o transacciones inexistentes. | K12: SUSPENDIDO | T12: RECLAMOS | U12: FINALIZADO SE RATIFICA
A13: 12 | B13: 1792299519001 | C13: COMPAÑÍA DE TRANSPORTE FLUVIAL CHIROISLA CIA. LTDA. | D13: SOCIEDAD | E13: ZONA 2 | F13: NAC-DNCOPEC16-00161996-M | G13: 42601.339 | H13: DZ2-GTRRSAV15-00000001-M | I13: 42621 | J13: Empresa inexistente, fantasma con actividades supuestas y transacciones inexistentes. | K13: SUSPENDIDO | T13: - | U13: -
A14: 13 | B14: 1900100361001 | C14: ORDOÑEZ BERMEO EDGAR | D14: PERSONA NATURAL | E14: ZONA 2 | F14: NAC-DNCOIOG16-00005307 | G14: 42689 | H14: DZ2-GTRRSAC16-00000003-M | I14: 42705 | J14: Persona natural con actividades supuestas y/o transacciones inexistentes. | K14: PASIVO | T14: - | U14: -
A15: 14 | B15: 1500686827001 | C15: SALAS ARELLANO WASHINGTON OSWALDO | D15: PERSONA NATURAL | E15: ZONA 2 | F15: NAC-DNCOIOG16-00005437 | G15: 42685 | H15: DZ2-GTRRSAC16-00000004-M | I15: 42705 | J15: Persona natural con actividades supuestas y/o transacciones inexistentes. | K15: SUSPENDIDO | T15: - | U15: -
A16: 15 | B16: 1501167298001 | C16: TORRES VILLON BRYAN JOEL | D16: PERSONA NATURAL | E16: ZONA 2 | F16: DZ2-GTROGEI17-00000003-M | G16: 43027 | H16: DZ2-GTRRASC17-00000003-M | I16: 43035 | J16: Persona natural con actividades supuestas y/o transacciones inexistentes. | K16: SUSPENDIDO | T16: - | U16: -
A17: 16 | B17: 0703249664001 | C17: VILLEGAS LIMONES JOSE PATRICIO | D17: PERSONA NATURAL | E17: ZONA 2 | F17: DZ2-GTROGEI17-00000002-M | G17: 43027 | H17: DZ2-GTRRASC17-00000002-M | I17: 43035 | J17: Persona natural con actividades supuestas y/o transacciones inexistentes. | K17: SUSPENDIDO | T17: - | U17: -
A18: 17 | B18: 0701820953001 | C18: VILLON PLACENCIO HENRY WANEY | D18: PERSONA NATURAL | E18: ZONA 2 | F18: NAC-DNCOIOG16-00005393 | G18: 42685 | H18: DZ2-GTRRSAC16-00000002-M | I18: 42705 | J18: Persona natural con actividades supuestas / transacciones inexistentes. | K18: SUSPENDIDO | T18: RECLAMOS | U18: FINALIZADO SE RATIFICA
A19: 18 | B19: 0702522228001 | C19: VILLON PLASENCIO AMARILIS NOEMI | D19: PERSONA NATURAL | E19: ZONA 2 | F19: DZ2-GTROGEI17-00000001-M | G19: 43027 | H19: DZ2-GTRRASC17-00000001-M | I19: 43035 | J19: Persona natural con actividades supuestas y/o transacciones inexistentes. | K19: SUSPENDIDO | T19: - | U19: -
A20: 19 | B20: 1802731651001 | C20: CARRASCO TAMAYO RICARDO SANTIAGO | D20: PERSONA NATURAL | E20: ZONA 3 | F20: DZ3-GCEOGEC19-00000001-M | G20: 43481 | H20: DZ3-GCERASC19-00000001-M | I20: 43502 | J20: Persona natural con actividades supuestas y/o transacciones inexistentes. | K20: SUSPENDIDO | T20: - | U20: -
A21: 20 | B21: 0603912627001 | C21: CASANOVA ZAMORA TANNIA ALEXANDRA | D21: PERSONA NATURAL | E21: ZONA 3 | F21: NAC-DNCOIOG16-00005444 | G21: 42685 | H21: PCH-GTRRASN16-00000208-M | I21: 42704 | J21: Persona natural con actividades supuestas y/o transacciones inexistentes. | K21: SUSPENDIDO | T21: RECLAMOS | U21: FINALIZADO SE RATIFICA
... A26: 25 | B26: 1312832569001 | C26: ARTEAGA MACIAS CARLOS ENRIQUE | D26: PERSONA NATURAL | E26: ZONA 4 | F26: NAC-DNCOIOG16-00005330 | G26: 42685 | H26: CMA-GPNRASC16-00000001-M | I26: 42733 | J26: Persona natural con actividades supuestas y/o transacciones inexistentes. | K26: SUSPENDIDO | T26: - | U26: -
A27: 26 | B27: 1312909870001 | C27: ARTURO ORTIZ MARIA ANABEL | D27: PERSONAS NATURALES | E27: ZONA 4 | F27: DZ4-GSOORIC18-00000008-M | G27: 43297 | H27: DZ4-GSOOIOC18-00000002-M | I27: 43321 | J27: Persona natural con actividades supuestas y/o transacciones inexistentes. | K27: ACTIVO | P27: CBC-CGTOGEC20-00000001-M CBC-CGTOGEC20-00000003-M | Q27: 19/10/2020 15/12/2020 | R27: ACEPTA | S27: 44257 | T27: - | U27: -
A28: 27 | B28: 0914707765001 | C28: ASENCIO DIAZ JULIO ERNESTO | D28: PERSONA NATURAL | E28: ZONA 4 | F28: NAC-DNCOIOG16-00005427 | G28: 42685 | H28: CMA-GPNRASC16-00000002-M | I28: 42733 | J28: Persona natural con actividades supuestas y/o transacciones inexistentes. | K28: SUSPENDIDO | T28: - | U28: -
A29: 28 | B29: 1311442527001 | C29: AVILA VELASCO GREGORIO ELIAS | D29: PERSONA NATURAL | E29: ZONA 4 | F29: CJI-CGTORIC18-00000002-M | G29: 43287 | H29: DZ4-GPNMGEI18-00000002-M | I29: 43298 | J29: Persona natural con actividades supuestas y/o transacciones inexistentes. | K29: SUSPENDIDO | T29: - | U29: -
A30: 29 | B30: 1309568952001 | C30: AVILEZ VELEZ OSCAR ARTURO | D30: PERSONA NATURAL | E30: ZONA 4 | F30: PSD-GTROGEC20-00000004-M | G30: 43882 | H30: PSD-GTRRASC20-00000005-M | I30: 44133 | J30: Persona natural con actividades supuestas y/o transacciones inexistentes. | K30: SUSPENDIDO | T30: - | U30: -
A31: 30 | B31: 1391776276001 | C31: BIOCIUDAD S.A. | D31: SOCIEDAD | E31: ZONA 4 | F31: DZ4-ASOOPEC17-00000001-M | G31: 43070 | H31: DZ4-ASORASC17-00000001-M | I31: 43089 | J31: Sociedad con transacciones inexistentes | K31: PASIVO | T31: - | U31: -
A32: 31 | B32: 1310021280001 | C32: BRAVO PARRAGA RICHAR ESTALIN | D32: PERSONA NATURAL | E32: ZONA 4 | F32: NAC-DNCOIOG16-00005404 | G32: 42685 | H32: CMA-GPNRASC16-00000003-M | I32: 42733 | J32: Persona natural con actividades supuestas y/o transacciones inexistentes. | K32: SUSPENDIDO | T32: - | U32: -
A33: 32 | B33: 0802192211001 | C33: CARVAJAL CASTILLO SARA YAQUELINE | D33: PERSONA NATURAL | E33: ZONA 4 | F33: PSD-GTROGEC20-00000002-M | G33: 43882 | H33: PSD-GTRRASC20-00000001-M | I33: 44133 | J33: Persona natural con actividades supuestas y/o transacciones inexistentes. | K33: SUSPENDIDO | T33: - | U33: -
A34: 33 | B34: 1315832509001 | C34: CASTRO GONGORA PEDRO CARLOS | D34: PERSONA NATURAL | E34: ZONA 4 | F34: DZ4-GPNOGEC17-00000009-M | G34: 43005 | H34: DZ4-GPNRASC17-00000004-M | I34: 43025 | J34: Persona natural con actividades supuestas y/o transacciones inexistentes. | K34: SUSPENDIDO | T34: - | U34: -
A35: 34 | B35: 1312956376001 | C35: CEDEÑO LOOR ANGEL ENRIQUE | D35: PERSONA NATURAL | E35: ZONA 4 | F35: DZ4-APNOPEC18-00000001-M | G35: 27, 30 Y 31 DE JULIO 2018 | H35: DZ4-APNRASC19-00000001-M | I35: 43696 | J35: Persona natural con actividades supuestas e inexistentes. | K35: SUSPENDIDO | T35: - | U35: -
A36: 35 | B36: 1309067005001 | C36: CEDEÑO ZAMBRANO RAMON ANTENOR | D36: PERSONAS NATURALES | E36: ZONA 4 | F36: DZ4-GPNOGEC17-00000016-M | G36: 43006 | H36: CCH-GPNRASC17-00000002-M | I36: 43025 | J36: Persona natural con actividades supuestas / transacciones inexistentes. | K36: ACTIVO | P36: 113142018OGTN000435 | Q36: 43479 | R36: ACEPTA | S36: 43881 | T36: - | U36: -
A37: 36 | B37: 1311432668001 | C37: CHAVEZ TRIVIÑO GINA MARIUXI | D37: PERSONA NATURAL | E37: ZONA 4 | F37: NAC-DNCOIOG16-00005329 | G37: 42685 | H37: CMA-GPNRASC16-00000004-M | I37: 42705 | J37: Persona natural con actividades supuestas / transacciones inexistentes. | K37: SUSPENDIDO | T37: - | U37: -
A38: 37 | B38: 1311949166001 | C38: CHOEZ MERA VICTOR MANUEL | D38: PERSONA NATURAL | E38: ZONA 4 | F38: NAC-DNCOIOG16-00005440 | G38: 42685 | H38: DZ4-GPNRASC16-00000008-M | I38: 42733 | J38: Persona natural con actividades supuestas / transacciones inexistentes. | K38: SUSPENDIDO | T38: - | U38: -
A39: 38 | B39: 0928978956001 | C39: CHUNG LOOR KENIA VANESSA | D39: PERSONA NATURAL | E39: ZONA 4 | F39: CCH-CGTOGEC18-00000001-M | G39: 43390 | H39: CCH-CGTRASC18-00000001-M | I39: 43398 | J39: Persona natural con actividades supuestas / transacciones inexistentes. | K39: SUSPENDIDO | T39: - | U39: -
A40: 39 | B40: 1391831536001 | C40: CONSTRUCCIONES CIVIL SUAREZ & MOYA CONCISUAMO CIA.LTDA. | D40: SOCIEDAD | E40: ZONA 4 | F40: CMA-CGTOFQV17-00000072-M | G40: 43006 | H40: CMA-CGTRASV17-00000002-M | I40: 43032 | J40: Persona natural con actividades supuestas o transacciones inexistentes. | K40: PASIVO | T40: - | U40: -
A41: 40 | B41: 0907365878001 | C41: CRESPO GRANIZO WILLIAM RODOLFO | D41: PERSONA NATURAL | E41: ZONA 4 | F41: DZ4-GPNOGEC17-00000018-M | G41: 43055 | H41: DZ4-CGTRASC17-00010001-M | I41: 43066 | J41: Persona natural con actividades supuestas / transacciones inexistentes. | K41: SUSPENDIDO | T41: - | U41: -
A42: 41 | B42: 1725062986001 | C42: CUENCA ALAVA YUBER DANIEL | D42: PERSONA NATURAL | E42: ZONA 4 | F42: NAC-DNCOIOG16-00005336 | G42: 42685 | H42: DZ4-GPNRASC16-00000009-M | I42: 42706 | J42: Persona natural con actividades supuestas y/o transacciones inexistentes. | K42: SUSPENDIDO | T42: - | U42: -
A43: 42 | B43: 1312797853001 | C43: CUENCA PILAY HERNAN FREDDY | D43: PERSONA NATURAL | E43: ZONA 4 | F43: NAC-DNCOIOG16-00005335 | G43: 42685 | H43: DZ4-GPNRASC16-00000010-M | I43: 42706 | J43: Persona natural con actividades supuestas y/o transacciones inexistentes. | K43: SUSPENDIDO | T43: - | U43: -
A44: 43 | B44: 1306767508001 | C44: DE LA CRUZ CEDEÑO PEDRO JOSE | D44: PERSONA NATURAL | E44: ZONA 4 | F44: NAC-DNCOIOG16-00005438 | G44: 42685 | H44: DZ4-GPNRASC16-00000011-M | I44: 42733 | J44: Persona natural con actividades supuestas y/o transacciones inexistentes. | K44: SUSPENDIDO | T44: - | U44: -
A45: 44 | B45: 1720320348001 | C45: DELGADO CHANGO EDISON DANIEL | D45: PERSONA NATURAL | E45: ZONA 4 | F45: CBC-GPNOPEC17-00000020-M | G45: 43077 | H45: CBC-GPNRASC17-00000010-M | I45: 43087 | J45: Persona natural con actividades supuestas / transacciones inexistentes. | K45: SUSPENDIDO | T45: - | U45: -
A46: 45 | B46: 1308368313001 | C46: DENDER PINARGOTE ROBERTO ESMITH | D46: PERSONA NATURAL | E46: ZONA 8 | F46: CBC-CGTOGEC18-00000002-M | G46: 43312 | H46: CBC-CGTRASC18-00000002-M | I46: 43325 | J46: Persona natural con actividades supuestas / transacciones inexistentes. | K46: SUSPENDIDO | M46: 42004 | N46: RESOLUCION | O46: 44433 | T46: RECURSOS DE REVISION | U46: FINALIZADO POR PERÍODOS
A47: 46 | B47: 1308948734001 | C47: FALCONES ERAZO RAFAEL EDUARDO | D47: PERSONA NATURAL | E47: ZONA 4 | F47: DZ4-GPNOGEC17-00000012-M | G47: 43006 | H47: DZ4-GPNRASC17-00000002-M | I47: 43025 | J47: Persona natural con actividades supuestas y/o transacciones inexistentes. | K47: SUSPENDIDO | T47: - | U47: -
A48: 47 | B48: 0801390329001 | C48: GARCES CASTILLO YOLANDA SORAIDA | D48: PERSONA NATURAL | E48: ZONA 4 | F48: PSD-GTROGEC20-00000009-M | G48: 43882 | H48: PSD-GTRRASC20-00000004-M | I48: 44133 | J48: Persona natural con actividades supuestas y/o transacciones inexistentes. | K48: SUSPENDIDO | T48: - | U48: -
A49: 48 | B49: 1311991903001 | C49: GARCIA MACIAS BETTY MELISA | D49: PERSONAS NATURALES | E49: ZONA 4 | F49: DZ4-GCEORIC18-00000009-M | G49: 43293 | H49: DZ4-GCEOIOC18-00000003-M | I49: 43301 | J49: Persona natural con actividades supuestas y/o transacciones inexistentes. | K49: ACTIVO | P49: 113142019OGTN000344 | Q49: 43822 | R49: ACEPTA | S49: 43843 | T49: - | U49: -
A50: 49 | B50: 0923046080001 | C50: GILCES PANTA CINDY PAMELA | D50: PERSONA NATURAL | E50: ZONA 4 | F50: CJI-CGTORIC18-00000003-M | G50: 43287 | H50: DZ4-GPNMGEI18-00000003-M | I50: 43298 | J50: Persona natural con actividades supuestas y/o transacciones inexistentes. | K50: SUSPENDIDO | T50: - | U50: -
A51: 50 | B51: 1308962719001 | C51: GOROZABEL GARCIA MIGUEL OCTAVIO | D51: PERSONA NATURAL | E51: ZONA 4 | F51: NAC-DNCOIOG16-00005458 | G51: 42685 | H51: DZ4-GPNRASC16-00000001-M | I51: 42733 | J51: Persona natural con actividades supuestas y/o transacciones inexistentes. | K51: SUSPENDIDO | T51: - | U51: -
A52: 51 | B52: 0931236673001 | C52: HUNGRIA YANCE BORIS DAVID | D52: PERSONA NATURAL | E52: ZONA 4 | F52: CBC-GPNOPEC17-00000014-M | G52: 43011 | H52: CBC-GPNRASC17-00000001-M | I52: 43020 | J52: Persona natural con actividades supuestas / transacciones inexistentes. | K52: SUSPENDIDO | T52: - | U52: -
A53: 52 | B53: 1305543520001 | C53: IBARRA MANZABA BERNY FRANCISCO | D53: PERSONA NATURAL | E53: ZONA 4 | F53: CBC-GPNOPEC17-00000019-M | G53: 43054 | H53: CBC-GPNRASC17-00000006-M | I53: 43062 | J53: Persona natural con actividades supuestas / transacciones inexistentes. | K53: SUSPENDIDO | T53: - | U53: -
A54: 53 | B54: 1303529513001 | C54: INTRIAGO MALO BENITO ALFONSO | D54: PERSONA NATURAL | E54: ZONA 4 | F54: DZ4-APNOPEC18-00000006-M | G54: 15, 16 Y 17 DE AGOSTO 2018 | H54: DZ4-APNRASC19-00000006-M | I54: 43696 | J54: Persona natural con actividades supuestas e inexistentes. | K54: SUSPENDIDO | T54: - | U54: -
A55: 54 | B55: 1312805656001 | C55: INTRIAGO SANDOVAL DARWIN CARLOS | D55: PERSONA NATURAL | E55: ZONA 4 | F55: DZ4-APNOPEC18-00000007-M | G55: 15, 16 Y 17 DE AGOSTO 2018 | H55: DZ4-APNRASC19-00000007-M | I55: 43696 | J55: Persona natural con actividades supuestas e inexistentes. | K55: SUSPENDIDO | T55: - | U55: -
A56: 55 | B56: 1313117119001 | C56: INTRIAGO SANDOVAL JOSE BENITO | D56: PERSONA NATURAL | E56: ZONA 4 | F56: DZ4-APNOPEC18-00000010-M | G56: 15, 16 Y 17 DE AGOSTO 2018 | H56: DZ4-APNRASC19-00000010-M | I56: 43696 | J56: Persona natural con actividades supuestas e inexistentes. | K56: SUSPENDIDO | T56: - | U56: -
A57: 56 | B57: 1304496613001 | C57: LOPEZ CEDEÑO RAMON ANTONIO | D57: PERSONA NATURAL | E57: ZONA 4 | F57: DZ4-GPNOGEC18-00000003-M | G57: 43371 | H57: DZ4-GPNRASC18-00000001-M | I57: 43395 | J57: Persona natural con actividades supuestas y/o transacciones inexistentes. | K57: SUSPENDIDO | T57: - | U57: -
A58: 57 | B58: 1391783345001 | C58: MANSATURIS S.A. | D58: SOCIEDAD | E58: ZONA 4 | F58: NAC-DNCOPEC16-00161622-M | G58: 42600.755 | H58: DZ4-GSORASC16-00000003-M | I58: 42629 | J58: Empresa inexistente | K58: SUSPENDIDO | T58: - | U58: -
A59: 58 | B59: 0916964885001 | C59: MENOSCAL BONILLA EDISON REIMUNDO | D59: PERSONA NATURAL | E59: ZONA 4 | F59: NAC-DNCOIOG16-00005331 | G59: 42685 | H59: CMA-GPNRASC16-00000005-M | I59: 42705 | J59: Persona natural con actividades supuestas y/o transacciones inexistentes. | K59: SUSPENDIDO | T59: - | U59: -
A60: 59 | B60: 1310484223001 | C60: MERA CALDERON GUADALUPE ISABEL | D60: PERSONA NATURAL | E60: ZONA 4 | F60: DZ4-APNOPEC18-00000005-M | G60: 43308 | H60: DZ4-APNRASC19-00000005-M | I60: 43676 | J60: Persona natural con actividades supuestas e inexistentes. | K60: SUSPENDIDO | T60: - | U60: -
A61: 60 | B61: 1306629328001 | C61: MERA CALDERON ROSA ELENA | D61: PERSONA NATURAL | E61: ZONA 4 | F61: CBC-GPNOPEC17-00000021-M | G61: 43077 | H61: CBC-GPNRASC17-00000007-M | I61: 43087 | J61: Persona natural con actividades supuestas y/o transacciones inexistentes. | K61: SUSPENDIDO | T61: RECLAMOS | U61: FINALIZADO SE RATIFICA
A62: 61 | B62: 1305556605001 | C62: MERA CEDEÑO JOM ITLER | D62: PERSONA NATURAL | E62: ZONA 4 | F62: NAC-DNCOIOG16-00005374 | G62: 42685 | H62: DZ4-GPNRASC16-00000002-M | I62: 42710 | J62: Persona natural con actividades supuestas y/o transacciones inexistentes. | K62: SUSPENDIDO | T62: - | U62: -
A63: 62 | B63: 1310349954001 | C63: MERA GARCIA MARIANA DEL JESUS | D63: PERSONA NATURAL | E63: ZONA 4 | F63: DZ4-GSOORIC18-00000006-M | G63: 43291 | H63: DZ4-GSOOIOC18-00000001-M | I63: 43321 | J63: Persona natural con actividades supuestas y/o transacciones inexistentes. | K63: SUSPENDIDO | T63: RECLAMOS | U63: FINALIZADO SE RATIFICA
A64: 63 | B64: 1310067267001 | C64: MERA MOREIRA DANIEL ANTONIO | D64: PERSONA NATURAL | E64: ZONA 4 | F64: NAC-DNCOIOG16-00005403 | G64: 42685 | H64: DZ4-GPNRASC16-00000005-M | I64: 42733 | J64: Persona natural con actividades supuestas y/o transacciones inexistentes. | K64: SUSPENDIDO | T64: - | U64: -
A65: 64 | B65: 1312348566001 | C65: MERO MERO FREDDY DANIEL | D65: PERSONA NATURAL | E65: ZONA 4 | F65: CJI-CGTORIC18-00000001-M | G65: 43287 | H65: DZ4-GPNRASC18-00000012-M | I65: 43300 | J65: Persona natural con actividades supuestas y/o transacciones inexistentes. | K65: SUSPENDIDO | T65: - | U65: -
A66: 65 | B66: 1312228156001 | C66: MERO SALAZAR FATIMA ALEXANDRA | D66: PERSONAS NATURALES | E66: ZONA 4 | F66: DZ4-GPNOGEC17-00000014-M | G66: 43006 | H66: CCH-GPNRASC17-00000001-M | I66: 43025 | J66: Persona natural con actividades supuestas / transacciones inexistentes. | K66: SUSPENDIDO | P66: 113142019OGTN000111 | Q66: 43595 | R66: ACEPTA | S66: 43595 | T66: - | U66: -
A67: 66 | B67: 1723272066001 | C67: MESTANZA TAPIA JOSE ALEXANDER | D67: PERSONA NATURAL | E67: ZONA 4 | F67: PSD-GTROGEC20-00000007-M | G67: 43879 | H67: PSD-GTRRASC20-00000006-M | I67: 44133 | J67: Persona natural con actividades supuestas y/o transacciones inexistentes. | K67: SUSPENDIDO | T67: RECLAMOS | U67: FINALIZADO SE RATIFICA
A68: 67 | B68: 1305642850001 | C68: MONCAYO ZAMBRANO JOSE LUIS | D68: PERSONA NATURAL | E68: ZONA 4 | F68: CBC-GPNOPEC17-00000018-M | G68: 43054 | H68: CBC-GPNRASC17-00000005-M | I68: 43062 | J68: Persona natural con actividades supuestas y/o transacciones inexistentes. | K68: SUSPENDIDO | T68: - | U68: -
A69: 68 | B69: 1310467582001 | C69: MONCAYO ZAMBRANO MARIA JOSEFA | D69: PERSONA NATURAL | E69: ZONA 4 | F69: DZ4-APNOPEC18-00000012-M | G69: 43308 | H69: DZ4-APNRASC19-00000008-M | I69: 43696 | J69: Persona natural con actividades supuestas e inexistentes. | K69: SUSPENDIDO | T69: - | U69: -
A70: 69 | B70: 1308351764001 | C70: MONCAYO ZAMBRANO MIGUEL ANTONIO | D70: PERSONA NATURAL | E70: ZONA 4 | F70: CBC-GPNOPEC17-00000022-M | G70: 43077 | H70: CBC-GPNRASC17-00000009-M | I70: 43087 | J70: Persona natural con actividades supuestas / transacciones inexistentes. | K70: SUSPENDIDO | T70: - | U70: -
A71: 70 | B71: 2390023955001 | C71: MORALES PEREIRA JHON FREDY | D71: PERSONA NATURAL | E71: ZONA 4 | F71: PSD-GTROGEC17-00000010-M | G71: 43005 | H71: PSD-GTRRASC17-00010001-M | I71: 43069 | J71: Persona natural con actividades supuestas y/o transacciones inexistentes. | K71: SUSPENDIDO | T71: - | U71: -
A72: 71 | B72: 1391789785001 | C72: MORBELU S.A. | D72: SOCIEDAD | E72: ZONA 4 | F72: NAC-DNCOPEC16-00161572-M | G72: 42600.755 | H72: DZ4-GSORASC16-00000002-M | I72: 42629 | J72: Empresa Inexistente | K72: SUSPENDIDO | T72: - | U72: -
A73: 72 | B73: 1315919371001 | C73: MOREIRA CEDEÑO ISIDRO ANTONIO | D73: PERSONA NATURAL | E73: ZONA 4 | F73: NAC-DNCOIOG16-00005408 | G73: 42685 | H73: DZ4-GPNRASC16-00000006-M | I73: 42733 | J73: Persona natural con actividades supuestas y/o transacciones inexistentes. | K73: SUSPENDIDO | T73: - | U73: -
A74: 73 | B74: 1315613305001 | C74: MOREIRA INTRIAGO LEIBER IVAN | D74: PERSONA NATURAL | E74: ZONA 4 | F74: DZ4-GPNOGEC17-00000009-M | G74: 43006 | H74: DZ4-GPNRASC17-00000005-M | I74: 43025 | J74: Persona natural con actividades supuestas y/o transacciones inexistentes. | K74: SUSPENDIDO | T74: - | U74: -
A75: 74 | B75: 1312992298001 | C75: PALADINES MARTINEZ GABRIELA LIZETH | D75: PERSONA NATURAL | E75: ZONA 4 | F75: CBC-GPNOPEC17-00000017-M | G75: 43011 | H75: CBC-GPNRASC17-00000004-M | I75: 43020 | J75: Persona natural con actividades supuestas / transacciones inexistentes. | K75: SUSPENDIDO | T75: - | U75: -
A76: 75 | B76: 1205597196001 | C76: PALADINEZ IBARRA JEISON REYNALDO | D76: PERSONA NATURAL | E76: ZONA 4 | F76: CBC-GPNOPEC17-00000025-M | G76: 43105 | H76: CBC-GPNRASC18-00000001-M | I76: 43115 | J76: Persona natural con actividades supuestas / transacciones inexistentes. | K76: SUSPENDIDO | T76: - | U76: -
A77: 76 | B77: 0911344323001 | C77: PARRA GALARZA IVAN LORENZO | D77: PERSONA NATURAL | E77: ZONA 4 | F77: NAC-DNCOIOG16-00005406 | G77: 42685 | H77: DZ4-GPNRASC16-00000003-M | I77: 42733 | J77: Persona natural con actividades supuestas y/o transacciones inexistentes. | K77: PASIVO | T77: - | U77: -
A78: 77 | B78: 1312824335001 | C78: PARRALES ARRUNATEGUI CRISTHIAN ALBERTO | D78: PERSONA NATURAL | E78: ZONA 4 | F78: CBC-GPNOPEC17-00000016-M | G78: 43011 | H78: CBC-GPNRASC17-00000003-M | I78: 43020 | J78: Persona natural con actividades supuestas / transacciones inexistentes. | K78: SUSPENDIDO | T78: - | U78: -
... A87: 86 | B87: 1313489294001 | C87: REYNA VILLAMAR CRISTOBAL ISRAEL | D87: PERSONA NATURAL | E87: ZONA 4 | F87: CBC-CGTOGEC18-00000004-M | G87: 43343 | H87: CBC-CGTRASC18-00000004-M | I87: 43404 | J87: Persona natural con actividades supuestas / transacciones inexistentes. | K87: SUSPENDIDO | T87: - | U87: -
A88: 87 | B88: 1314101153001 | C88: RIVADENEIRA ZAMORA FELIX FERNANDO | D88: PERSONA NATURAL | E88: ZONA 4 | F88: DZ4-APNOPEC18-00000004-M | G88: 15, 16 Y 17 DE AGOSTO 2018 | H88: DZ4-APNRASC19-00000004-M | I88: 43696 | J88: Persona natural con actividades supuestas e inexistentes. | K88: SUSPENDIDO | T88: - | U88: -
A89: 88 | B89: 1306549187001 | C89: RIVAS PICO MARIA ELIZABETH | D89: PERSONA NATURAL | E89: ZONA 4 | F89: NAC-DNCOIOG16-00005454 | G89: 42685 | H89: DZ4-GPNRASC16-00000014-M | I89: 42705 | J89: Persona natural con actividades supuestas / transacciones inexistentes. | K89: SUSPENDIDO | T89: - | U89: -
A90: 89 | B90: 2300468457001 | C90: RODRIGUEZ MERA EVELYN MARIVI | D90: PERSONA NATURAL | E90: ZONA 4 | F90: PSD-GTROGEC20-00000008-M | G90: 43882 | H90: PSD-GTRRASC20-00000003-M | I90: 44133 | J90: Persona natural con actividades supuestas y/o transacciones inexistentes. | K90: SUSPENDIDO | T90: - | U90: -
A91: 90 | B91: 1302714736001 | C91: ROMERO GARCES RAMON ANTONIO | D91: PERSONA NATURAL | E91: ZONA 4 | F91: DZ4-APNOPEC18-00000009-M | G91: 15, 16 Y 17 DE AGOSTO 2018 | H91: DZ4-APNRASC19-00000009-M | I91: 43696 | J91: Persona natural con actividades supuestas e inexistentes. | K91: SUSPENDIDO | T91: - | U91: -
A92: 91 | B92: 1309066551001 | C92: SALTOS SALTOS WILDER ADALBERTO | D92: PERSONA NATURAL | E92: ZONA 4 | F92: NAC-DNCOIOG16-00005405 | G92: 42685 | H92: DZ4-GPNRASC16-00000015-M | I92: 42712 | J92: Persona natural con actividades supuestas y/o transacciones inexistentes. | K92: SUSPENDIDO | T92: - | U92: -
A93: 92 | B93: 1306630441001 | C93: STOPPER ROJAS ROBERTO JAVIER | D93: PERSONA NATURAL | E93: ZONA 4 | F93: DZ4-GPNOGEC17-00000013-M | G93: 43006 | H93: CCH-GPNRASC17-00000003-M | I93: 43025 | J93: Persona natural con actividades supuestas / transacciones inexistentes. | K93: SUSPENDIDO | T93: - | U93: -
A94: 93 | B94: 1391787944001 | C94: TIERRA SOUTH ECUADOR S.A. TERSEC | D94: SOCIEDAD | E94: ZONA 4 | F94: NAC-DNCOPEC16-00161794-M | G94: 42600.755 | H94: DZ4-GSORASC16-00000004-M | I94: 42626 | J94: Empresa inexistente | K94: SUSPENDIDO | T94: - | U94: -
A95: 94 | B95: 2300289614001 | C95: VIDAL TUAREZ ERICKA LOURDES | D95: PERSONA NATURAL | E95: ZONA 4 | F95: PSD-APNOGEC19-00000002-M | G95: 15, 16 Y 17 DE AGOSTO 2018 | H95: PSD-APNRASC19-00000001-M | I95: 43665 | J95: Persona natural con actividades supuestas e inexistentes. | K95: SUSPENDIDO | T95: - | U95: -
A96: 95 | B96: 1724850746001 | C96: ZAMBRANO CAGUA ESTEFANIA CLARA | D96: PERSONA NATURAL | E96: ZONA 4 | F96: PSD-GTROGEC20-00000006-M | G96: 43882 | H96: PSD-GTRRASC20-00000002-M | I96: 44133 | J96: Persona natural con actividades supuestas y/o transacciones inexistentes. | K96: SUSPENDIDO | T96: - | U96: -
A97: 96 | B97: 1304793381001 | C97: ZAMBRANO CASTAÑEDA RITA CATALINA | D97: PERSONA NATURAL | E97: ZONA 4 | F97: DZ4-APNOPEC18-00000003-M | G97: 15, 16 Y 17 DE AGOSTO 2018 | H97: DZ4-APNRASC19-00000003-M | I97: 43696 | J97: Persona natural con actividades supuestas e inexistentes. | K97: SUSPENDIDO | T97: - | U97: -
A98: 97 | B98: 1314150002001 | C98: ZAMBRANO ZAMBRANO EDY FERNANDO | D98: PERSONAS NATURALES | E98: ZONA 4 | F98: DZ4-GPNOGEC17-00000015-M | G98: 43006 | H98: CCH-GPNRASC17-00000004-M | I98: 43025 | J98: Persona natural con actividades supuestas / transacciones inexistentes. | K98: ACTIVO | P98: 113142018OGTN000226 | Q98: 43271 | R98: ACEPTA | S98: 43647 | T98: - | U98: -
A99: 98 | B99: 1310484769001 | C99: ZAVALA ROLDAN ANIBAL FERNANDO | D99: PERSONA NATURAL | E99: ZONA 4 | F99: NAC-DNCOIOG16-00005359 | G99: 42685 | H99: DZ4-GPNRASC16-00000017-M | I99: 42705 | J99: Persona natural con actividades supuestas / transacciones inexistentes. | K99: SUSPENDIDO | T99: - | U99: -
A100: 99 | B100: 1308114857001 | C100: ZAVALA ROLDAN JONNY AGENOR | D100: PERSONA NATURAL | E100: ZONA 4 | F100: NAC-DNCOIOG16-00005333 | G100: 42685 | H100: DZ4-GPNRASC16-00000016-M | I100: 42705 | J100: Persona natural con actividades supuestas / transacciones inexistentes. | K100: SUSPENDIDO | T100: - | U100: -
A101: 100 | B101: 0702227372001 | C101: AGUIRRE ANDINO GUIDO RICHARD | D101: PERSONA NATURAL | E101: ZONA 5 | F101: NAC-DNCOIOG16-00005392 | G101: 42685 | H101: PSE-GTRRASN16-00000005-M | I101: 42760 | J101: Persona natural con actividades supuestas / transacciones inexistentes. | K101: SUSPENDIDO | T101: - | U101: -
A102: 101 | B102: 0992848774001 | C102: CASAESCROW S.A | D102: SOCIEDAD | E102: ZONA 5 | F102: PSE-GTROGEV17-00000007-M | G102: 43049 | H102: DZ5-GTRRASC17-00010001-M | I102: 43059 | J102: Empresa inexistente o fantasma | K102: PASIVO | T102: - | U102: -
A103: 102 | B103: 0992673249001 | C103: CATERING INTERPRISE CAINPRI S.A. | D103: SOCIEDAD | E103: ZONA 5 | F103: NAC-DNCOPEC16-00161841-M | G103: 42601.339 | H103: PSE-GTRRASC16-00000003-M | I103: 42622 | J103: Empresa inexistente o fantasma | K103: SUSPENDIDO | T103: - | U103: -
A104: 103 | B104: 0591720872001 | C104: CONSTIDOR S.A. | D104: SOCIEDAD | E104: ZONA 5 | F104: NAC-DNCOPEC16-00161634-M | G104: 42600.755 | H104: DZ5-GTRRASV16-00000001-M | I104: 42622 | J104: Empresa inexistente, fantasma o supuesta, o sociedad con actividades supuestas y/o transacciones inexistentes | K104: SUSPENDIDO | T104: RECURSOS DE REVISION | U104: POR RESOLVER
A105: 104 | B105: 1205818576001 | C105: CONTRERAS MORAN FREDDY DUBERLI | D105: PERSONA NATURAL | E105: ZONA 5 | F105: DZ5-GTROGEC19-00000025-M | G105: 43580 | H105: DZ5-GTRRASC19-00000001-M | I105: 43593 | J105: Persona natural con actividades supuestas / transacciones inexistentes. | K105: SUSPENDIDO | T105: - | U105: -
A106: 105 | B106: 1291725437001 | C106: CREPECAM S.A CONSTRUCCIONES Y REPARACIONES DE EQUIPOS CAMINEROS Y MAQUINARIAS PESADAS | D106: SOCIEDAD | E106: ZONA 5 | F106: NAC-DNCOPEC16-00161684-M | G106: 42600.756 | H106: DZ5-GTRRASV16-00000003-M | I106: 42629 | J106: Empresa inexistente, fantasma o supuesta, o sociedad con actividades supuestas y/o transacciones inexistentes | K106: SUSPENDIDO | T106: - | U106: -
A107: 106 | B107: 2091757047001 | C107: GALAPAGOS VISION VISIONISLAND CIA. LTDA | D107: SOCIEDAD | E107: ZONA 5 | F107: NAC-DNCOIOG16-00005466 | G107: 42685 | H107: CPB-CGTRASV16-00000001-M | I107: 42709 | J107: Persona jurídica con actividades supuestas / transacciones inexistentes | K107: SUSPENDIDO | T107: - | U107: -
A108: 107 | B108: 0992670584001 | C108: INCONSESA S.A. | D108: SOCIEDAD | E108: ZONA 5 | F108: NAC-DNCOPEC16-00161774-M | G108: 42600.756 | H108: PSE-GTRRASC16-00000002-M | I108: 42622 | J108: Empresa inexistente o Fantasma | K108: SUSPENDIDO | T108: RECLAMOS | U108: FINALIZADO SE RATIFICA
A109: 108 | B109: 1291739462001 | C109: MERELPAR S.A. | D109: SOCIEDAD | E109: ZONA 5 | F109: NAC-DNCOPEC16-00161928-M | G109: 42601.339 | H109: DZ5-GTRRASV16-00000005-M | I109: 42629 | J109: Empresa inexistente, fantasma o supuesta, o sociedad con actividades supuestas y/o transacciones inexistentes | K109: SUSPENDIDO | T109: - | U109: -
A110: 109 | B110: 1201596853001 | C110: MORENO BRAVO ANTONIO MARIOL | D110: PERSONA NATURAL | E110: ZONA 5 | F110: NAC-DNCOIOG16-00005373 | G110: 42685 | H110: CQU-CGTRASN16-00000001-M | I110: 42760 | J110: Persona natural con actividades supuestas / transacciones inexistentes. | K110: SUSPENDIDO | T110: - | U110: -
... A118: 117 | B118: 0301556361001 | C118: CORDERO ALBARRACIN MARIA TERESA | D118: PERSONA NATURAL | E118: ZONA 6 | F118: PCN-APNOIUC18-00000002-M | G118: 43280 | H118: PCN-APNRSNC18-00000002-M | I118: 43305 | J118: Persona natural con actividades supuestas y/o transacciones inexistentes. | K118: SUSPENDIDO | T118: - | U118: -
A119: 118 | B119: 0704095884001 | C119: CORDOVA GUAMAN CARLOS NELSON | D119: PERSONAS NATURALES | E119: ZONA 6 | F119: DZ6-GTROGEC18-00000042-M | G119: 43308 | H119: DZ6-GTRRASC18-00000007-M | I119: 43362 | J119: Persona natural con actividades supuestas / transacciones inexistentes. | K119: SUSPENDIDO | P119: 107012022OGTN005266 | Q119: 44900 | R119: ACEPTA | T119: - | U119: -
...
